colourout/__init__.py
colourout/eprintc.py
colourout/printc.py
colourout/process_styles.py
colourout/styles.py
colourout-0.1.1.dist-info/LICENSE.MD
colourout-0.1.1.dist-info/METADATA
colourout-0.1.1.dist-info/WHEEL
colourout-0.1.1.dist-info/top_level.txt
colourout-0.1.1.dist-info/RECORD
