Metadata-Version: 2.1
Name: colourout
Version: 0.1.1
Summary: A Python package for printing coloured text to the terminal.
Home-page: https://github.com/sam-kenney/colourout
Author: Sam Kenney
Author-email: sam.kenney@me.com
License: MIT
Platform: UNKNOWN
Classifier: Programming Language :: Python :: 3
Classifier: License :: OSI Approved :: MIT License
Classifier: Operating System :: OS Independent
Requires-Python: >=3.6
